model_railway_signals/__init__.py
model_railway_signals/__main__.py
model_railway_signals/editor.py
model_railway_signals/run_layout.py
model_railway_signals/run_routes.py
model_railway_signals/schematic.py
model_railway_signals/scripting.py
model_railway_signals/settings.py
model_railway_signals/common/__init__.py
model_railway_signals/common/common_complete.py
model_railway_signals/common/common_compound.py
model_railway_signals/common/common_extensible.py
model_railway_signals/common/common_simple.py
model_railway_signals/docs/networking_guide.pdf
model_railway_signals/docs/quickstart_guide.pdf
model_railway_signals/docs/sensor_node_guide.pdf
model_railway_signals/docs/setup_guide.pdf
model_railway_signals/docs/signalling_node_guide.pdf
model_railway_signals/examples/absolute_block_example.sig
model_railway_signals/examples/automation_colour_light_example.sig
model_railway_signals/examples/automation_semaphore_example.sig
model_railway_signals/examples/colour_light_signals.sig
model_railway_signals/examples/complex_trackwork.sig
model_railway_signals/examples/holt_signal_box.sig
model_railway_signals/examples/mqtt_networked_example.sig
model_railway_signals/examples/networking1-node1.sig
model_railway_signals/examples/networking1-node2.sig
model_railway_signals/examples/nx_route_setting_example.sig
model_railway_signals/examples/one_touch_routes_example.sig
model_railway_signals/examples/quickstart_example1.sig
model_railway_signals/examples/quickstart_example1a.sig
model_railway_signals/examples/quickstart_example2.sig
model_railway_signals/examples/quickstart_example3.sig
model_railway_signals/examples/quickstart_example4.sig
model_railway_signals/examples/quickstart_example5.sig
model_railway_signals/examples/quickstart_example6.sig
model_railway_signals/examples/quickstart_track_occupancy.sig
model_railway_signals/examples/semaphore_signals.sig
model_railway_signals/examples/sensor_node.sig
model_railway_signals/examples/sidings_example.sig
model_railway_signals-6.1.0.dist-info/METADATA
model_railway_signals-6.1.0.dist-info/WHEEL
model_railway_signals-6.1.0.dist-info/licenses/LICENSE
model_railway_signals-6.1.0.dist-info/RECORD
