Metadata-Version: 2.4
Name: model-railway-signals
Version: 6.1.0
Summary: Create your own DCC model railway signalling scheme
Project-URL: Homepage, https://github.com/johnrm174/model-railway-signalling
Project-URL: Issues, https://github.com/johnrm174/model-railway-signalling/issues
Project-URL: Website, https://www.model-railway-signalling.co.uk/
Author-email: johnrm174 <johnrm17418@gmail.com>
Maintainer-email: johnrm174 <johnrm17418@gmail.com>
License-File: LICENSE
Classifier: License :: OSI Approved :: GNU General Public License (GPL)
Classifier: Operating System :: OS Independent
Classifier: Programming Language :: Python :: 3
Requires-Python: >=3.7
Requires-Dist: paho-mqtt
Requires-Dist: pyserial
